{"actions":[{"id":"153;a","state":"SUCCESS","returnValue":{"returnValue":"/primarycarepatientregistration","cacheable":true},"error":[]},{"id":"154;a","state":"SUCCESS","returnValue":{"returnValue":"/primarycarepatientregistration","cacheable":true},"error":[]},{"id":"155;a","state":"SUCCESS","returnValue":{"returnValue":"/primarycarepatientregistration","cacheable":true},"error":[]},{"id":"156;a","state":"SUCCESS","returnValue":{"returnValue":"/primarycarepatientregistration","cacheable":true},"error":[]},{"id":"157;a","state":"SUCCESS","returnValue":{"cacheable":false},"error":[]}],"context":{"mode":"PROD","app":"siteforce:communityApp","contextPath":"/primarycarepatientregistration/s/sfsites","pathPrefix":"/primarycarepatientregistration","fwuid":"VXZJYkJtTFAtX2RjOGFiVmZaelpqQTk4bkk0bVJhZGJCWE9mUC1IZXZRbmcyNDguMTAuNC01LjAuOQ","mlr":1,"loaded":{"APPLICATION@markup://siteforce:communityApp":"BjwfLR6ajQeK0GMFT8Kw0A","COMPONENT@markup://instrumentation:o11ySecondaryLoader":"VZ2Rg7MN_BaoV_0Qlk5pAw"},"globalValueProviders":[{"type":"$Global","values":{"eswConfigDeveloperName":{"writable":true,"defaultValue":""},"isVoiceOver":{"writable":true,"defaultValue":false},"setupAppContextId":{"writable":true,"defaultValue":""},"density":{"writable":true,"defaultValue":""},"srcdoc":{"writable":false,"defaultValue":false},"appContextId":{"writable":true,"defaultValue":""},"dynamicTypeSize":{"writable":true,"defaultValue":""}}}],"enableAccessChecks":true,"apce":1,"dns":"c","rns":["omnistudio"],"ls":1,"lairn":[],"laerc":[],"lav":"60","ln":1,"csp":1,"mna":{"lightning":"interop"},"lff":{"ENABLE_MIXED_SHADOW_MODE":false,"ENABLE_LEGACY_SCOPE_TOKENS":false,"DISABLE_LIGHT_DOM_UNSCOPED_CSS":false},"arse":1,"acaf":1,"services":["markup://lightning:configProvider","markup://force:salesforceScopedModuleResolver","markup://force:ldsEngineCreator","markup://instrumentation:locatorService"]},"perfSummary":{"version":"core","request":382,"actions":{"153;a":{"total":58,"db":25},"154;a":{"total":32,"db":11},"155;a":{"total":34,"db":13},"156;a":{"total":27,"db":10},"157;a":{"total":35,"db":9}},"actionsTotal":186,"overhead":0}}